{
  "version": "7",
  "dialect": "postgresql",
  "entries": [
    {
      "idx": 0,
      "version": "7",
      "when": 1770830685891,
      "tag": "0000_kind_abomination",
      "breakpoints": true
    },
    {
      "idx": 1,
      "version": "7",
      "when": 1770878889542,
      "tag": "0001_past_ultimatum",
      "breakpoints": true
    },
    {
      "idx": 2,
      "version": "7",
      "when": 1770978241299,
      "tag": "0002_high_hardball",
      "breakpoints": true
    },
    {
      "idx": 3,
      "version": "7",
      "when": 1770983089942,
      "tag": "0003_tough_khan",
      "breakpoints": true
    }
  ]
}